odoo10_addon_attachment_preview-10.0.1.3.0.99.dev3-py3.8-nspkg.pth
odoo/addons/attachment_preview/README.rst
odoo/addons/attachment_preview/__init__.py
odoo/addons/attachment_preview/__manifest__.py
odoo/addons/attachment_preview/i18n/attachment_preview.pot
odoo/addons/attachment_preview/i18n/nl.po
odoo/addons/attachment_preview/i18n/sl.po
odoo/addons/attachment_preview/models/__init__.py
odoo/addons/attachment_preview/models/ir_attachment.py
odoo/addons/attachment_preview/readme/CONTRIBUTORS.rst
odoo/addons/attachment_preview/readme/CREDITS.rst
odoo/addons/attachment_preview/readme/DESCRIPTION.rst
odoo/addons/attachment_preview/readme/INSTALL.rst
odoo/addons/attachment_preview/readme/USAGE.rst
odoo/addons/attachment_preview/static/description/icon.png
odoo/addons/attachment_preview/static/description/index.html
odoo/addons/attachment_preview/static/description/screenshot-paginator.png
odoo/addons/attachment_preview/static/description/screenshot-split.png
odoo/addons/attachment_preview/static/lib/ViewerJS/compatibility.js
odoo/addons/attachment_preview/static/lib/ViewerJS/example.local.css
odoo/addons/attachment_preview/static/lib/ViewerJS/index.html
odoo/addons/attachment_preview/static/lib/ViewerJS/pdf.js
odoo/addons/attachment_preview/static/lib/ViewerJS/pdf.worker.js
odoo/addons/attachment_preview/static/lib/ViewerJS/pdfjsversion.js
odoo/addons/attachment_preview/static/lib/ViewerJS/text_layer_builder.js
odoo/addons/attachment_preview/static/lib/ViewerJS/ui_utils.js
odoo/addons/attachment_preview/static/lib/ViewerJS/webodf.js
odoo/addons/attachment_preview/static/lib/ViewerJS/images/kogmbh.png
odoo/addons/attachment_preview/static/lib/ViewerJS/images/nlnet.png
odoo/addons/attachment_preview/static/lib/ViewerJS/images/texture.png
odoo/addons/attachment_preview/static/lib/ViewerJS/images/toolbarButton-download.png
odoo/addons/attachment_preview/static/lib/ViewerJS/images/toolbarButton-fullscreen.png
odoo10_addon_attachment_preview-10.0.1.3.0.99.dev3.dist-info/METADATA
odoo10_addon_attachment_preview-10.0.1.3.0.99.dev3.dist-info/WHEEL
odoo10_addon_attachment_preview-10.0.1.3.0.99.dev3.dist-info/namespace_packages.txt
odoo10_addon_attachment_preview-10.0.1.3.0.99.dev3.dist-info/top_level.txt
odoo10_addon_attachment_preview-10.0.1.3.0.99.dev3.dist-info/RECORD
